flextoolslib/__init__.py
flextoolslib/code/FLExTools.py
flextoolslib/code/FTCollections.py
flextoolslib/code/FTConfig.py
flextoolslib/code/FTDialogs.py
flextoolslib/code/FTModuleClass.py
flextoolslib/code/FTModules.py
flextoolslib/code/FTReport.py
flextoolslib/code/Help.py
flextoolslib/code/UICollections.py
flextoolslib/code/UIGlobal.py
flextoolslib/code/UIMain.py
flextoolslib/code/UIModuleBrowser.py
flextoolslib/code/UIModuleInfo.py
flextoolslib/code/UIModulesList.py
flextoolslib/code/UIProjectChooser.py
flextoolslib/code/UIReport.py
flextoolslib/code/UISettings.py
flextoolslib/code/__init__.py
flextoolslib/docs/FLExTools Help.pdf
flextoolslib/docs/FLExTools Programming.pdf
flextoolslib/icons/Flextools.ico
flextoolslib/icons/Module.ico
flextoolslib/icons/readme.txt
flextoolslib/icons/Fugue/cross_circle.png
flextoolslib/icons/Fugue/exclamation.png
flextoolslib/icons/Fugue/information.png
flextoolslib/icons/IconBuffet Redmond Studio/Flex_16.gif
flextoolslib/icons/IconBuffet Redmond Studio/add_16.gif
flextoolslib/icons/IconBuffet Redmond Studio/applications_16.gif
flextoolslib/icons/IconBuffet Redmond Studio/arrow-down_16.gif
flextoolslib/icons/IconBuffet Redmond Studio/arrow-forward-!_16.gif
flextoolslib/icons/IconBuffet Redmond Studio/arrow-forward-double-!_16.gif
flextoolslib/icons/IconBuffet Redmond Studio/arrow-forward-double_16.gif
flextoolslib/icons/IconBuffet Redmond Studio/arrow-forward_16.gif
flextoolslib/icons/IconBuffet Redmond Studio/arrow-up_16.gif
flextoolslib/icons/IconBuffet Redmond Studio/copy_16.gif
flextoolslib/icons/IconBuffet Redmond Studio/delete_16.gif
flextoolslib/icons/IconBuffet Redmond Studio/documents_16.gif
flextoolslib/icons/IconBuffet Redmond Studio/folder-closed_16.gif
flextoolslib/icons/IconBuffet Redmond Studio/folder-open_16.gif
flextoolslib/icons/IconBuffet Redmond Studio/trash_16.gif
flextoolslib/locales/de/LC_MESSAGES/flextools.mo
flextoolslib/locales/de/LC_MESSAGES/flextools.po
flextoolslib/locales/es/LC_MESSAGES/flextools.mo
flextoolslib-2025.8.26.dist-info/licenses/LICENSE.txt
flextoolslib-2025.8.26.dist-info/METADATA
flextoolslib-2025.8.26.dist-info/WHEEL
flextoolslib-2025.8.26.dist-info/top_level.txt
flextoolslib-2025.8.26.dist-info/RECORD
