Metadata-Version: 2.4
Name: flextoolslib
Version: 2025.8.26
Summary: A tool for running Python scripts on FieldWorks Language Explorer projects
Home-page: https://github.com/cdfarrow/flextools
Author: Craig Farrow
Author-email: flextoolshelp@gmail.com
License: "GPL-2.0-or-later"
Platform: 'Windows'
Classifier: Intended Audience :: Developers
Classifier: Programming Language :: Python :: 3.9
Classifier: Programming Language :: Python :: 3.10
Classifier: Programming Language :: Python :: 3.11
Classifier: Programming Language :: Python :: 3.12
Classifier: Programming Language :: Python :: 3.13
Classifier: Topic :: Text Processing :: Linguistic
Classifier: Topic :: Database
Requires-Python: <3.14,>=3.9
License-File: LICENSE.txt
Requires-Dist: flexlibs>=1.2.7.1
Requires-Dist: cdfutils<1.2,>=1.1.2
Dynamic: license-file
